{
    "1_-_The_Knife_Of_Never_Letting_Go_Chaos_Walking_1__by_Patrick_Ness.epub.po": "0.0",
    "1_Eragon_by_Paolini_Christopher.epub.po": "25.4",
    "AnthonyHorowitzMagpieMurders.epub.po": "67.2",
    "Chris_Miller_-_Chip_War.epub.po": "1.4",
    "Crime_and_Punishment.mobi.po": "96.9",
    "Forbidden Nation A History of Taiwan - Manthorpe Jonathan.azw3.po": "91.4",
    "It_by_Stephen_King.epub.po": "93.0",
    "Leviathan_Wakes_Expanse_1_-_James_S_A_Corey.epub.po": "66.1",
    "The Technological Republic Hard Power, Soft Belief, and the Future of the West (Alexander C Karp  Nicholas W. Zamiska) (Z-Library).azw3.po": "55.1",
    "Theories of International Politics and Zombies.epub.po": "28.2",
    "crime-and-punishment.pdf.po": "12.5",
    "fromthirdworldtofirst.epub.po": "18.6",
    "theblindwatchmaker.epub.po": "86.3",
    "worthdyingfor.epub.po": "71.2",
    "The_Shining_-_Stephen_King.epub.po": "78.4",
    "The_Sword_of_Kaigen_by_M_L_Wang_A_Theonite_War_Companion_Novel.epub.po": "96.5",
    "The Eye of the World - Robert Jordan.epub.po": "93.5",
    "Empire_of_Silence_-_Christopher_Ruocchio.epub.po": "96.7",
    "Howling_Dark_-_Christopher_Ruocchio.epub.po": "16.5",
    "theoriesofinternationalpolitics": "97.9",
    "forbiddennation": "95.4",
    "1984": "92.1",
    "abriefhistoryofthemiddleeast": "91.0",
    "windandtruth": "99.4",
    "9780765334343.epub.po": "53.9"
}
